README.md
setup.py
ssebop/__init__.py
ssebop/collector.py
ssebop/ssebop.py
ssebop.egg-info/PKG-INFO
ssebop.egg-info/SOURCES.txt
ssebop.egg-info/dependency_links.txt
ssebop.egg-info/requires.txt
ssebop.egg-info/top_level.txt
ssebop_app/__init__.py
ssebop_app/cli.py
ssebop_app/config.py
ssebop_app/image.py
ssebop_app/paths.py
ssebop_app/runspec_script.py
tests/__init__.py
tests/test_app.py
tests/test_ssebop.py
tests/test_suite.py